docs/__init__.py
gb_module/__init__.py
gb_module/core/__init__.py
gb_module/core/backup_module.py
gb_module/core/backup_result.py
gb_module/core/base_module.py
gb_module/core/base_result.py
gb_module/core/restore_result.py
gb_module/core/retrieve_result.py
gb_module/core/storage_module.py
gb_module/core/storage_result.py
gb_module/testing/__init__.py
gb_module/testing/util/__init__.py
gb_module/testing/util/backup_result_test_util.py
gb_module/testing/util/module_test_util.py
gb_module/utils/__init__.py
gb_module/utils/selenium_util.py
tests/__init__.py
tests/test_base_module.py
gb_module-0.0.2.dist-info/LICENSE
gb_module-0.0.2.dist-info/METADATA
gb_module-0.0.2.dist-info/WHEEL
gb_module-0.0.2.dist-info/top_level.txt
gb_module-0.0.2.dist-info/RECORD
