Metadata-Version: 2.1
Name: gb-module
Version: 0.0.2
Summary: Generic Backupy Module Library
Author: Martin Rader
Classifier: Programming Language :: Python :: 3
Classifier: License :: OSI Approved :: MIT License
Classifier: Operating System :: OS Independent
Requires-Python: >=3.6
License-File: LICENSE
Requires-Dist: selenium (<5.0,>=4.7.2)
